Metadata-Version: 2.1
Name: dryenv
Version: 0.0.1
Summary: Simple DRY configuration with environment variables and pydantic.
Home-page: http://github.com/alexmojaki/dryenv
Author: Alex Hall
Author-email: alex.mojaki@gmail.com
License: MIT
Platform: UNKNOWN
Classifier: Intended Audience :: Developers
Classifier: Programming Language :: Python :: 3.6
Classifier: Programming Language :: Python :: 3.7
Classifier: Programming Language :: Python :: 3.8
Classifier: License :: OSI Approved :: MIT License
Classifier: Operating System :: OS Independent
Provides-Extra: tests
